Metadata-Version: 2.4
Name: hack4u-courses-library
Version: 0.1.5
Summary: Libreria de prueba - Consultar los cursos de un modulo
Home-page: https://hack4u.io
Author: Juanhez
Dynamic: author
Dynamic: description
Dynamic: description-content-type
Dynamic: home-page
Dynamic: summary
